{
  "_comment": "東証 17 業種 -> 代表個股。ticker 為 TSE 4 位數 code，yfinance 存取時需加 .T 後綴。可自行擴充。",
  "_source": "curated large/mid-cap representatives per TSE 17 sector",
  "食品": [
    {"code": "2502", "name": "アサヒグループHD"},
    {"code": "2503", "name": "キリンHD"},
    {"code": "2501", "name": "サッポロHD"},
    {"code": "2801", "name": "キッコーマン"},
    {"code": "2802", "name": "味の素"},
    {"code": "2897", "name": "日清食品HD"},
    {"code": "2269", "name": "明治HD"},
    {"code": "2267", "name": "ヤクルト本社"},
    {"code": "2264", "name": "森永乳業"},
    {"code": "2270", "name": "雪印メグミルク"},
    {"code": "2201", "name": "森永製菓"},
    {"code": "2206", "name": "江崎グリコ"},
    {"code": "2212", "name": "山崎製パン"},
    {"code": "2229", "name": "カルビー"},
    {"code": "2282", "name": "日本ハム"},
    {"code": "2593", "name": "伊藤園"},
    {"code": "2607", "name": "不二製油グループ本社"},
    {"code": "2002", "name": "日清製粉グループ本社"},
    {"code": "2875", "name": "東洋水産"},
    {"code": "2871", "name": "ニチレイ"},
    {"code": "2531", "name": "宝HD"},
    {"code": "1333", "name": "マルハニチロ"},
    {"code": "2809", "name": "キユーピー"},
    {"code": "2810", "name": "ハウス食品グループ本社"},
    {"code": "2811", "name": "カゴメ"}
  ],
  "エネルギー資源": [
    {"code": "1605", "name": "INPEX"},
    {"code": "5019", "name": "出光興産"},
    {"code": "5020", "name": "ENEOS HD"},
    {"code": "5021", "name": "コスモエネルギーHD"},
    {"code": "1662", "name": "石油資源開発"}
  ],
  "建設・資材": [
    {"code": "1801", "name": "大成建設"},
    {"code": "1802", "name": "大林組"},
    {"code": "1803", "name": "清水建設"},
    {"code": "1812", "name": "鹿島建設"},
    {"code": "1808", "name": "長谷工コーポレーション"},
    {"code": "1820", "name": "西松建設"},
    {"code": "5076", "name": "インフロニアHD"},
    {"code": "1925", "name": "大和ハウス工業"},
    {"code": "1928", "name": "積水ハウス"},
    {"code": "1911", "name": "住友林業"},
    {"code": "1963", "name": "日揮HD"},
    {"code": "5232", "name": "住友大阪セメント"},
    {"code": "5233", "name": "太平洋セメント"},
    {"code": "5332", "name": "TOTO"},
    {"code": "5938", "name": "LIXIL"},
    {"code": "5333", "name": "日本碍子"},
    {"code": "5201", "name": "AGC"},
    {"code": "5202", "name": "日本板硝子"},
    {"code": "5214", "name": "日本電気硝子"},
    {"code": "5301", "name": "東海カーボン"},
    {"code": "1951", "name": "エクシオグループ"},
    {"code": "1878", "name": "大東建託"},
    {"code": "1893", "name": "五洋建設"},
    {"code": "5334", "name": "日本特殊陶業"}
  ],
  "素材・化学": [
    {"code": "3401", "name": "帝人"},
    {"code": "3402", "name": "東レ"},
    {"code": "3405", "name": "クラレ"},
    {"code": "3407", "name": "旭化成"},
    {"code": "4004", "name": "レゾナック・HD"},
    {"code": "4005", "name": "住友化学"},
    {"code": "4021", "name": "日産化学"},
    {"code": "4042", "name": "東ソー"},
    {"code": "4061", "name": "デンカ"},
    {"code": "4063", "name": "信越化学工業"},
    {"code": "4091", "name": "日本酸素HD"},
    {"code": "4183", "name": "三井化学"},
    {"code": "4188", "name": "三菱ケミカルG"},
    {"code": "4202", "name": "ダイセル"},
    {"code": "4203", "name": "住友ベークライト"},
    {"code": "4204", "name": "積水化学工業"},
    {"code": "4205", "name": "日本ゼオン"},
    {"code": "4208", "name": "UBE"},
    {"code": "4182", "name": "三菱ガス化学"},
    {"code": "4272", "name": "日本化薬"},
    {"code": "4401", "name": "ADEKA"},
    {"code": "4403", "name": "日油"},
    {"code": "4452", "name": "花王"},
    {"code": "4612", "name": "日本ペイントHD"},
    {"code": "4613", "name": "関西ペイント"},
    {"code": "4631", "name": "DIC"},
    {"code": "4911", "name": "資生堂"},
    {"code": "4912", "name": "ライオン"},
    {"code": "4917", "name": "マンダム"},
    {"code": "4919", "name": "ミルボン"},
    {"code": "4922", "name": "コーセー"},
    {"code": "4927", "name": "ポーラ・オルビスHD"},
    {"code": "4901", "name": "富士フイルムHD"},
    {"code": "4902", "name": "コニカミノルタ"},
    {"code": "6988", "name": "日東電工"}
  ],
  "医薬品": [
    {"code": "4502", "name": "武田薬品"},
    {"code": "4503", "name": "アステラス製薬"},
    {"code": "4506", "name": "住友ファーマ"},
    {"code": "4507", "name": "塩野義製薬"},
    {"code": "4519", "name": "中外製薬"},
    {"code": "4523", "name": "エーザイ"},
    {"code": "4528", "name": "小野薬品"},
    {"code": "4530", "name": "久光製薬"},
    {"code": "4536", "name": "参天製薬"},
    {"code": "4540", "name": "ツムラ"},
    {"code": "4543", "name": "テルモ"},
    {"code": "4544", "name": "H.U.グループHD"},
    {"code": "4568", "name": "第一三共"},
    {"code": "4578", "name": "大塚HD"},
    {"code": "4151", "name": "協和キリン"},
    {"code": "4587", "name": "ペプチドリーム"}
  ],
  "自動車・輸送機": [
    {"code": "7201", "name": "日産自動車"},
    {"code": "7202", "name": "いすゞ自動車"},
    {"code": "7203", "name": "トヨタ自動車"},
    {"code": "7205", "name": "日野自動車"},
    {"code": "7211", "name": "三菱自動車"},
    {"code": "7259", "name": "アイシン"},
    {"code": "7261", "name": "マツダ"},
    {"code": "7267", "name": "ホンダ"},
    {"code": "7269", "name": "スズキ"},
    {"code": "7270", "name": "SUBARU"},
    {"code": "7272", "name": "ヤマハ発動機"},
    {"code": "6201", "name": "豊田自動織機"},
    {"code": "6902", "name": "デンソー"},
    {"code": "7276", "name": "小糸製作所"},
    {"code": "7282", "name": "豊田合成"},
    {"code": "3116", "name": "トヨタ紡織"},
    {"code": "7240", "name": "NOK"},
    {"code": "7238", "name": "曙ブレーキ工業"},
    {"code": "5108", "name": "ブリヂストン"},
    {"code": "5101", "name": "横浜ゴム"},
    {"code": "5110", "name": "住友ゴム工業"},
    {"code": "7012", "name": "川崎重工業"},
    {"code": "7003", "name": "三井E&S"}
  ],
  "鉄鋼・非鉄": [
    {"code": "5401", "name": "日本製鉄"},
    {"code": "5411", "name": "JFE HD"},
    {"code": "5406", "name": "神戸製鋼所"},
    {"code": "5423", "name": "東京製鐵"},
    {"code": "5471", "name": "大同特殊鋼"},
    {"code": "5482", "name": "愛知製鋼"},
    {"code": "5541", "name": "大平洋金属"},
    {"code": "5631", "name": "日本製鋼所"},
    {"code": "5706", "name": "三井金属"},
    {"code": "5711", "name": "三菱マテリアル"},
    {"code": "5713", "name": "住友金属鉱山"},
    {"code": "5714", "name": "DOWA HD"},
    {"code": "5801", "name": "古河電気工業"},
    {"code": "5802", "name": "住友電気工業"},
    {"code": "5803", "name": "フジクラ"},
    {"code": "5741", "name": "UACJ"},
    {"code": "5393", "name": "ニチアス"}
  ],
  "機械": [
    {"code": "6103", "name": "オークマ"},
    {"code": "6113", "name": "アマダ"},
    {"code": "6135", "name": "牧野フライス製作所"},
    {"code": "6141", "name": "DMG森精機"},
    {"code": "6146", "name": "ディスコ"},
    {"code": "6201", "name": "豊田自動織機"},
    {"code": "6273", "name": "SMC"},
    {"code": "6301", "name": "コマツ"},
    {"code": "6302", "name": "住友重機械工業"},
    {"code": "6305", "name": "日立建機"},
    {"code": "6326", "name": "クボタ"},
    {"code": "6361", "name": "荏原"},
    {"code": "6367", "name": "ダイキン工業"},
    {"code": "6465", "name": "ホシザキ"},
    {"code": "6471", "name": "日本精工"},
    {"code": "6472", "name": "NTN"},
    {"code": "6473", "name": "ジェイテクト"},
    {"code": "6481", "name": "THK"},
    {"code": "6586", "name": "マキタ"},
    {"code": "6954", "name": "ファナック"},
    {"code": "6005", "name": "三浦工業"},
    {"code": "6268", "name": "ナブテスコ"},
    {"code": "6324", "name": "ハーモニック・ドライブ・システムズ"},
    {"code": "7011", "name": "三菱重工業"},
    {"code": "7013", "name": "IHI"},
    {"code": "9962", "name": "ミスミグループ本社"}
  ],
  "電機・精密": [
    {"code": "6501", "name": "日立製作所"},
    {"code": "6503", "name": "三菱電機"},
    {"code": "6504", "name": "富士電機"},
    {"code": "6506", "name": "安川電機"},
    {"code": "6594", "name": "ニデック"},
    {"code": "6701", "name": "NEC"},
    {"code": "6702", "name": "富士通"},
    {"code": "6724", "name": "セイコーエプソン"},
    {"code": "6752", "name": "パナソニック HD"},
    {"code": "6758", "name": "ソニーグループ"},
    {"code": "6762", "name": "TDK"},
    {"code": "6770", "name": "アルプスアルパイン"},
    {"code": "6841", "name": "横河電機"},
    {"code": "6857", "name": "アドバンテスト"},
    {"code": "6861", "name": "キーエンス"},
    {"code": "6869", "name": "シスメックス"},
    {"code": "6902", "name": "デンソー"},
    {"code": "6920", "name": "レーザーテック"},
    {"code": "6963", "name": "ローム"},
    {"code": "6971", "name": "京セラ"},
    {"code": "6976", "name": "太陽誘電"},
    {"code": "6981", "name": "村田製作所"},
    {"code": "7731", "name": "ニコン"},
    {"code": "7733", "name": "オリンパス"},
    {"code": "7735", "name": "SCREEN HD"},
    {"code": "7741", "name": "HOYA"},
    {"code": "7751", "name": "キヤノン"},
    {"code": "7752", "name": "リコー"},
    {"code": "8035", "name": "東京エレクトロン"},
    {"code": "6146", "name": "ディスコ"},
    {"code": "6857", "name": "アドバンテスト"},
    {"code": "6727", "name": "ワコム"},
    {"code": "6723", "name": "ルネサスエレクトロニクス"},
    {"code": "7912", "name": "大日本印刷"},
    {"code": "7911", "name": "TOPPAN HD"}
  ],
  "情報通信・サービスその他": [
    {"code": "9432", "name": "NTT"},
    {"code": "9433", "name": "KDDI"},
    {"code": "9434", "name": "ソフトバンク"},
    {"code": "9984", "name": "ソフトバンクグループ"},
    {"code": "4307", "name": "野村総合研究所"},
    {"code": "4684", "name": "オービック"},
    {"code": "4689", "name": "LINEヤフー"},
    {"code": "4704", "name": "トレンドマイクロ"},
    {"code": "4716", "name": "日本オラクル"},
    {"code": "4751", "name": "サイバーエージェント"},
    {"code": "4755", "name": "楽天グループ"},
    {"code": "3659", "name": "ネクソン"},
    {"code": "3765", "name": "ガンホー・オンライン"},
    {"code": "4324", "name": "電通グループ"},
    {"code": "4385", "name": "メルカリ"},
    {"code": "2371", "name": "カカクコム"},
    {"code": "2413", "name": "エムスリー"},
    {"code": "2432", "name": "ディー・エヌ・エー"},
    {"code": "2121", "name": "MIXI"},
    {"code": "4776", "name": "サイボウズ"},
    {"code": "6532", "name": "ベイカレント・コンサルティング"},
    {"code": "9449", "name": "GMOインターネットグループ"},
    {"code": "7974", "name": "任天堂"},
    {"code": "7832", "name": "バンダイナムコHD"},
    {"code": "9697", "name": "カプコン"},
    {"code": "9684", "name": "スクウェア・エニックスHD"}
  ],
  "電気・ガス": [
    {"code": "9501", "name": "東京電力HD"},
    {"code": "9502", "name": "中部電力"},
    {"code": "9503", "name": "関西電力"},
    {"code": "9504", "name": "中国電力"},
    {"code": "9505", "name": "北陸電力"},
    {"code": "9506", "name": "東北電力"},
    {"code": "9507", "name": "四国電力"},
    {"code": "9508", "name": "九州電力"},
    {"code": "9509", "name": "北海道電力"},
    {"code": "9513", "name": "J-POWER"},
    {"code": "9531", "name": "東京ガス"},
    {"code": "9532", "name": "大阪ガス"},
    {"code": "9533", "name": "東邦ガス"}
  ],
  "運輸・物流": [
    {"code": "9001", "name": "東武鉄道"},
    {"code": "9005", "name": "東急"},
    {"code": "9007", "name": "小田急電鉄"},
    {"code": "9008", "name": "京王電鉄"},
    {"code": "9009", "name": "京成電鉄"},
    {"code": "9020", "name": "東日本旅客鉄道"},
    {"code": "9021", "name": "西日本旅客鉄道"},
    {"code": "9022", "name": "東海旅客鉄道"},
    {"code": "9041", "name": "近鉄グループHD"},
    {"code": "9042", "name": "阪急阪神HD"},
    {"code": "9045", "name": "京阪HD"},
    {"code": "9048", "name": "名古屋鉄道"},
    {"code": "9064", "name": "ヤマトHD"},
    {"code": "9101", "name": "日本郵船"},
    {"code": "9104", "name": "商船三井"},
    {"code": "9107", "name": "川崎汽船"},
    {"code": "9147", "name": "NIPPON EXPRESS HD"},
    {"code": "9201", "name": "日本航空"},
    {"code": "9202", "name": "ANA HD"},
    {"code": "9301", "name": "三菱倉庫"}
  ],
  "商社・卸売": [
    {"code": "8001", "name": "伊藤忠商事"},
    {"code": "8002", "name": "丸紅"},
    {"code": "8015", "name": "豊田通商"},
    {"code": "8031", "name": "三井物産"},
    {"code": "8053", "name": "住友商事"},
    {"code": "8058", "name": "三菱商事"},
    {"code": "2768", "name": "双日"},
    {"code": "8020", "name": "兼松"},
    {"code": "3105", "name": "日清紡HD"},
    {"code": "8060", "name": "キヤノンマーケティングジャパン"},
    {"code": "8113", "name": "ユニ・チャーム"}
  ],
  "小売": [
    {"code": "3086", "name": "J.フロント リテイリング"},
    {"code": "3099", "name": "三越伊勢丹HD"},
    {"code": "3382", "name": "セブン&アイ・HD"},
    {"code": "8252", "name": "丸井グループ"},
    {"code": "8233", "name": "高島屋"},
    {"code": "8267", "name": "イオン"},
    {"code": "3391", "name": "ツルハHD"},
    {"code": "3349", "name": "コスモス薬品"},
    {"code": "3088", "name": "マツキヨココカラ&カンパニー"},
    {"code": "9843", "name": "ニトリHD"},
    {"code": "9831", "name": "ヤマダHD"},
    {"code": "3048", "name": "ビックカメラ"},
    {"code": "3197", "name": "すかいらーくHD"},
    {"code": "3543", "name": "コメダHD"},
    {"code": "7550", "name": "ゼンショーHD"},
    {"code": "9861", "name": "吉野家HD"},
    {"code": "9983", "name": "ファーストリテイリング"},
    {"code": "8227", "name": "しまむら"},
    {"code": "7453", "name": "良品計画"},
    {"code": "3092", "name": "ZOZO"},
    {"code": "2670", "name": "ABC-MART"},
    {"code": "2730", "name": "エディオン"},
    {"code": "8273", "name": "イズミ"},
    {"code": "7532", "name": "パン・パシフィック・インターナショナルHD"}
  ],
  "銀行": [
    {"code": "8306", "name": "三菱UFJフィナンシャルG"},
    {"code": "8316", "name": "三井住友フィナンシャルG"},
    {"code": "8411", "name": "みずほフィナンシャルG"},
    {"code": "7186", "name": "コンコルディア・フィナンシャルG"},
    {"code": "8303", "name": "新生銀行(SBI新生)"},
    {"code": "8308", "name": "りそなHD"},
    {"code": "8331", "name": "千葉銀行"},
    {"code": "5831", "name": "しずおかフィナンシャルG"},
    {"code": "8354", "name": "ふくおかフィナンシャルG"},
    {"code": "8358", "name": "スルガ銀行"},
    {"code": "8359", "name": "八十二銀行"},
    {"code": "8366", "name": "滋賀銀行"},
    {"code": "8377", "name": "ほくほくフィナンシャルG"},
    {"code": "7337", "name": "ちゅうぎんフィナンシャルG"},
    {"code": "8418", "name": "山口フィナンシャルG"},
    {"code": "8473", "name": "SBIHD"},
    {"code": "8570", "name": "イオンFS"},
    {"code": "8572", "name": "アコム"},
    {"code": "8591", "name": "オリックス"},
    {"code": "7182", "name": "ゆうちょ銀行"},
    {"code": "7181", "name": "かんぽ生命保険"}
  ],
  "金融(除く銀行)": [
    {"code": "8591", "name": "オリックス"},
    {"code": "8601", "name": "大和証券グループ本社"},
    {"code": "8604", "name": "野村HD"},
    {"code": "8697", "name": "日本取引所グループ"},
    {"code": "8725", "name": "MS&AD インシュアランスG"},
    {"code": "8750", "name": "第一生命HD"},
    {"code": "8766", "name": "東京海上HD"},
    {"code": "8795", "name": "T&D HD"},
    {"code": "8630", "name": "SOMPO HD"},
    {"code": "8572", "name": "アコム"},
    {"code": "7181", "name": "かんぽ生命保険"},
    {"code": "8424", "name": "芙蓉総合リース"},
    {"code": "8425", "name": "みずほリース"},
    {"code": "8439", "name": "東京センチュリー"},
    {"code": "8566", "name": "リコーリース"}
  ],
  "不動産": [
    {"code": "8801", "name": "三井不動産"},
    {"code": "8802", "name": "三菱地所"},
    {"code": "8804", "name": "東京建物"},
    {"code": "8830", "name": "住友不動産"},
    {"code": "3289", "name": "東急不動産HD"},
    {"code": "3231", "name": "野村不動産HD"},
    {"code": "3003", "name": "ヒューリック"},
    {"code": "3288", "name": "オープンハウスグループ"},
    {"code": "8848", "name": "レオパレス21"},
    {"code": "8892", "name": "日本エスコン"},
    {"code": "3291", "name": "飯田グループHD"}
  ],
  "指数": [
    {"code": "^N225", "name": "日経平均"},
    {"code": "1306.T", "name": "TOPIX (1306)"},
    {"code": "1305.T", "name": "TOPIX Core30 (1305)"}
  ]
}
